foodeo_core/__init__.py
foodeo_core/clients/__init__.py
foodeo_core/clients/services/__init__.py
foodeo_core/clients/services/clients/__init__.py
foodeo_core/clients/services/clients/abstractions/__init__.py
foodeo_core/clients/services/clients/abstractions/icreate_user_client_service.py
foodeo_core/commands/__init__.py
foodeo_core/commands/entities/__init__.py
foodeo_core/commands/entities/modifiers.py
foodeo_core/commands/repositories/__init__.py
foodeo_core/commands/repositories/interfaces.py
foodeo_core/commands/services/__init__.py
foodeo_core/commands/services/commands_tips.py
foodeo_core/commands/services/corrections_from_command.py
foodeo_core/commands/services/price_and_discount.py
foodeo_core/commands/services/request_for_corrections.py
foodeo_core/commands/services/corrections/__init__.py
foodeo_core/commands/services/corrections/deleted_products.py
foodeo_core/commands/services/corrections/modifiers_tree_delta.py
foodeo_core/commands/services/corrections/orchestator.py
foodeo_core/commands/services/corrections/product_qty_delta.py
foodeo_core/dataclasses/__init__.py
foodeo_core/dataclasses/result.py
foodeo_core/orders/__init__.py
foodeo_core/orders/repositories/__init__.py
foodeo_core/orders/repositories/interfaces.py
foodeo_core/orders/services/__init__.py
foodeo_core/orders/services/promotions_validation_services.py
foodeo_core/payments/__init__.py
foodeo_core/payments/entities/__init__.py
foodeo_core/payments/entities/interface.py
foodeo_core/payments/entities/cashlogy/__init__.py
foodeo_core/payments/entities/cashlogy/payment_params.py
foodeo_core/payments/entities/cashlogy/start_payment_data.py
foodeo_core/payments/entities/cashmatic/__init__.py
foodeo_core/payments/entities/cashmatic/cancel_payment_data.py
foodeo_core/payments/entities/cashmatic/payment_params.py
foodeo_core/payments/entities/cashmatic/start_payment_data.py
foodeo_core/payments/entities/dojo/__init__.py
foodeo_core/payments/entities/dojo/cancel_payment_data.py
foodeo_core-0.1.18.dist-info/METADATA
foodeo_core-0.1.18.dist-info/WHEEL
foodeo_core-0.1.18.dist-info/RECORD
