Metadata-Version: 2.4
Name: foodeo-core
Version: 0.1.18
Summary: Foodeo Core Domain.
Project-URL: Homepage, https://github.com/Foodeo/foodeo-core
Project-URL: Repository, https://github.com/Foodeo/foodeo-core
Project-URL: Issues, https://github.com/Foodeo/foodeo-core/issues
Author-email: OmarSRolo <chicomtz.sr@gmail.com>, ramsy19980104 <busto0498@gmail.com>
License: MIT
Keywords: domain,foodeo
Classifier: Development Status :: 3 - Alpha
Classifier: Intended Audience :: Developers
Classifier: License :: OSI Approved :: MIT License
Classifier: Operating System :: OS Independent
Classifier: Programming Language :: Python :: 3
Classifier: Programming Language :: Python :: 3.10
Classifier: Programming Language :: Python :: 3.11
Classifier: Programming Language :: Python :: 3.12
Requires-Python: >=3.10
Requires-Dist: pydantic>=2.12.2
